eachk/eachk.py
eachk-0.1.0.dist-info/METADATA
eachk-0.1.0.dist-info/WHEEL
eachk-0.1.0.dist-info/top_level.txt
eachk-0.1.0.dist-info/RECORD
