Metadata-Version: 2.4
Name: eachk
Version: 0.1.0
Summary: A package for skipping every k-th iteration
Author-email: Alexa Korabelnikov <you@example.com>
License: MIT
Classifier: Programming Language :: Python :: 3
Classifier: License :: OSI Approved :: MIT License
Classifier: Operating System :: OS Independent
Requires-Python: >=3.6
